<dashboard>
    <id>default</id>
    <title>Default</title>
    <columnCount>2</columnCount>
    <widgets>
        <cn.com.rexen.notice.webapp.wicket.widget.NoticeWidget>
            <id>system.notice</id>
            <title>公告</title>
            <collapsed>false</collapsed>
            <settings/>
            <location>
                <column>0</column>
                <row>0</row>
            </location>
        </cn.com.rexen.notice.webapp.wicket.widget.NoticeWidget>
    </widgets>
</dashboard>